aiko_services/__init__.py
aiko_services/elements/gstreamer/__init__.py
aiko_services/elements/gstreamer/utilities.py
aiko_services/elements/gstreamer/video_camera_reader.py
aiko_services/elements/gstreamer/video_file_reader.py
aiko_services/elements/gstreamer/video_file_writer.py
aiko_services/elements/gstreamer/video_reader.py
aiko_services/elements/gstreamer/video_stream_reader.py
aiko_services/elements/gstreamer/video_stream_writer.py
aiko_services/elements/gstreamer/video_test.py
aiko_services/elements/media/__init__.py
aiko_services/elements/media/audio_io.py
aiko_services/elements/media/common_io.py
aiko_services/elements/media/image_io.py
aiko_services/elements/media/image_pipeline_0.json
aiko_services/elements/media/image_pipeline_1.json
aiko_services/elements/media/images_to_video.py
aiko_services/elements/media/text_io.py
aiko_services/elements/media/text_pipeline_0.json
aiko_services/elements/media/video_example.py
aiko_services/elements/media/video_io.py
aiko_services/elements/media/video_pipeline_0.json
aiko_services/elements/media/video_to_images.json
aiko_services/elements/media/video_to_images.py
aiko_services/elements/media/video_to_images.yaml
aiko_services/elements/media/webcam_io.py
aiko_services/elements/media/webcam_pipeline_0.json
aiko_services/elements/media/webcam_pipeline_1.json
aiko_services/elements/media/data_in/in_00.jpeg
aiko_services/elements/media/data_in/in_00.txt
aiko_services/elements/media/data_in/in_01.jpeg
aiko_services/elements/media/data_in/in_01.txt
aiko_services/elements/media/data_in/in_02.jpeg
aiko_services/elements/media/data_in/in_02.txt
aiko_services/examples/aloha_honua/ReadMe.md
aiko_services/examples/aloha_honua/aiko_dashboard_0a.png
aiko_services/examples/aloha_honua/aiko_diagram_0.excalidraw
aiko_services/examples/aloha_honua/aiko_diagram_0.png
aiko_services/examples/aloha_honua/aloha_honua_0.py
aiko_services/examples/aruco_marker/aruco.py
aiko_services/examples/aruco_marker/aruco_pipeline_0.json
aiko_services-0.6.dist-info/METADATA
aiko_services-0.6.dist-info/WHEEL
aiko_services-0.6.dist-info/entry_points.txt
aiko_services-0.6.dist-info/licenses/LICENSE
aiko_services-0.6.dist-info/RECORD
