Metadata-Version: 2.3
Name: aiko_services
Version: 0.6
Summary: Distributed embedded service framework for A.I and robotics
Author-email: Andy Gelme <geekscape@gmail.com>
License-File: LICENSE
Keywords: ai,distributed,embedded,framework,internet of things,machine learning,media,robotics
Classifier: Intended Audience :: Developers
Classifier: License :: OSI Approved :: Apache Software License
Classifier: Operating System :: MacOS
Classifier: Operating System :: POSIX :: Linux
Classifier: Operating System :: Unix
Classifier: Programming Language :: Python :: 3.9
Classifier: Programming Language :: Python :: 3.10
Classifier: Programming Language :: Python :: 3.11
Classifier: Programming Language :: Python :: 3.12
Classifier: Programming Language :: Python :: 3.13
Classifier: Topic :: Scientific/Engineering :: Artificial Intelligence
Classifier: Topic :: Software Development :: Libraries :: Application Frameworks
Classifier: Topic :: System :: Distributed Computing
Requires-Python: <=3.13.0,>=3.9.0
Requires-Dist: asciimatics~=1.15.0
Requires-Dist: avro-validator~=1.2.1
Requires-Dist: avro~=1.12.0
Requires-Dist: click~=8.1.7
Requires-Dist: numpy~=2.1.2
Requires-Dist: paho-mqtt<2.0.0,>=1.6.1
Requires-Dist: pillow~=10.4.0
Requires-Dist: pyperclip~=1.9.0
Requires-Dist: requests~=2.32.3
Requires-Dist: transitions~=0.9.2
Requires-Dist: wrapt~=1.16.0
